bssagent/__init__.py
bssagent/auth/__init__.py
bssagent/auth/api_key_management.py
bssagent/auth/authentication_with_key.py
bssagent/core/__init__.py
bssagent/core/agent_session.py
bssagent/core/base_agent.py
bssagent/database/__init__.py
bssagent/database/db_connection.py
bssagent/database/db_type.py
bssagent/database/memory.py
bssagent/environment/__init__.py
bssagent/examples/__init__.py
bssagent/examples/agent/__init__.py
bssagent/examples/agent/agent.py
bssagent/examples/agent/data_privacy_middleware_example.py
bssagent/examples/agent/server.py
bssagent/examples/agent/state.py
bssagent/examples/agent/tools.py
bssagent/examples/mcp/init_mcp_tools.py
bssagent/examples/rag/extract_data.py
bssagent/examples/rag/query_vector_db.py
bssagent/examples/rag/rag_pipeline.py
bssagent/examples/server/auth_key/__init__.py
bssagent/examples/server/auth_key/advanced_auth_example.py
bssagent/examples/server/auth_key/complete_auth_example.py
bssagent/examples/server/auth_key/simple_auth_example.py
bssagent/examples/tutorials/4_1_base_agent.py
bssagent/examples/tutorials/4_2_user_session.py
bssagent/examples/tutorials/4_3_database_integration.py
bssagent/examples/tutorials/4_4_advanced_agent.py
bssagent/examples/tutorials/4_5_server_api.py
bssagent/examples/tutorials/4_6_rag_integration.py
bssagent/examples/tutorials/4_7_applied_security.py
bssagent/examples/tutorials/4_8_authentication_with_key.py
bssagent/infrastructure/__init__.py
bssagent/infrastructure/server.py
bssagent/mcp/__init__.py
bssagent/mcp/mcp_connection.py
bssagent/mcp/mcp_enhanced_agent.py
bssagent/mcp/mcp_integrator.py
bssagent/mcp/mcp_tool_wrapper.py
bssagent/rag/__init__.py
bssagent/rag/embedding_models.py
bssagent/rag/rag.py
bssagent/rag/text_extractor.py
bssagent/rag/vector_dbs.py
bssagent/security/__init__.py
bssagent/security/data_privacy_manager.py
bssagent/security/prompt_sanitizer.py
bssagent/security/rate_limit.py
bssagent/shared/__init__.py
bssagent-0.1.1.dist-info/licenses/LICENSE
bssagent-0.1.1.dist-info/METADATA
bssagent-0.1.1.dist-info/WHEEL
bssagent-0.1.1.dist-info/entry_points.txt
bssagent-0.1.1.dist-info/top_level.txt
bssagent-0.1.1.dist-info/RECORD
