Metadata-Version: 2.4
Name: bssagent
Version: 0.1.1
Summary: BSS Agent – A simple AI agent framework based on LangGraph
Author: BSS Agent Team
Maintainer: BSS Agent Team
License: MIT
Project-URL: Homepage, https://github.com/bssagent/bssagent
Project-URL: Documentation, https://bssagent.readthedocs.io
Project-URL: Repository, https://github.com/bssagent/bssagent.git
Project-URL: Bug Tracker, https://github.com/bssagent/bssagent/issues
Project-URL: Changelog, https://github.com/bssagent/bssagent/blob/main/CHANGELOG.md
Keywords: ai,agent,langchain,langgraph,business,automation
Classifier: Development Status :: 3 - Alpha
Classifier: Intended Audience :: Developers
Classifier: License :: OSI Approved :: MIT License
Classifier: Programming Language :: Python :: 3
Classifier: Programming Language :: Python :: 3.8
Classifier: Programming Language :: Python :: 3.9
Classifier: Programming Language :: Python :: 3.10
Classifier: Programming Language :: Python :: 3.11
Classifier: Programming Language :: Python :: 3.12
Classifier: Topic :: Software Development :: Libraries :: Python Modules
Classifier: Topic :: Scientific/Engineering :: Artificial Intelligence
Requires-Python: >=3.8
License-File: LICENSE
Requires-Dist: langchain>=0.3.26
Requires-Dist: langgraph>=0.5.3
Requires-Dist: langchain-community>=0.0.20
Requires-Dist: langchain-openai>=0.3.0
Requires-Dist: langchain-google-genai>=2.1.6
Requires-Dist: langchain-anthropic>=0.3.17
Requires-Dist: langchain-deepseek>=0.1.0
Requires-Dist: langchain-ollama>=0.3.0
Requires-Dist: langgraph-supervisor>=0.0.28
Requires-Dist: langgraph-checkpoint-postgres>=2.0.21
Requires-Dist: langgraph-checkpoint-mongodb>=0.1.4
Requires-Dist: langgraph-checkpoint-mysql>=2.0.15
Requires-Dist: langgraph-checkpoint-redis>=0.0.8
Requires-Dist: langgraph-checkpoint-sqlite>=2.0.10
Requires-Dist: python-dotenv>=1.0.0
Requires-Dist: pydantic>=2.0.0
Requires-Dist: requests>=2.31.0
Requires-Dist: aiohttp>=3.8.0
Requires-Dist: websockets>=11.0.0
Requires-Dist: beautifulsoup4>=4.11.0
Requires-Dist: urllib3>=1.26.0
Requires-Dist: trafilatura>=1.5.0
Requires-Dist: PyPDF2>=3.0.0
Requires-Dist: python-docx>=0.8.11
Requires-Dist: pandas>=1.5.0
Requires-Dist: openpyxl>=3.0.0
Requires-Dist: docx2txt>=0.9
Requires-Dist: xlrd>=2.0.0
Requires-Dist: python-pptx>=0.6.0
Requires-Dist: rtfparse>=0.9.5
Requires-Dist: pyarrow>=10.0.0
Requires-Dist: fastavro>=1.7.0
Requires-Dist: lxml>=4.9.0
Requires-Dist: html5lib>=1.1
Requires-Dist: nltk>=3.8
Requires-Dist: textstat>=0.7.0
Requires-Dist: weaviate-client>=4.16.3
Requires-Dist: langchain-chroma>=0.2.5
Requires-Dist: sqlalchemy>=2.0.0
Requires-Dist: alembic>=1.11.0
Requires-Dist: psycopg2-binary>=2.9.0
Requires-Dist: redis>=4.5.0
Requires-Dist: PyMySQL>=1.1.0
Requires-Dist: celery>=5.3.0
Requires-Dist: boto3>=1.26.0
Requires-Dist: azure-mgmt-compute>=30.0.0
Requires-Dist: google-cloud-compute>=1.10.0
Requires-Dist: cryptography>=41.0.0
Requires-Dist: jwt>=1.3.1
Requires-Dist: bcrypt>=4.0.0
Requires-Dist: fastapi>=0.100.0
Requires-Dist: slowapi>=0.1.9
Requires-Dist: uvicorn>=0.20.0
Requires-Dist: docker>=6.1.0
Requires-Dist: kubernetes>=26.1.0
Provides-Extra: dev
Requires-Dist: pytest>=7.4.0; extra == "dev"
Requires-Dist: pytest-asyncio>=0.21.0; extra == "dev"
Requires-Dist: pytest-cov>=4.1.0; extra == "dev"
Requires-Dist: pytest-mock>=3.11.0; extra == "dev"
Requires-Dist: black>=23.0.0; extra == "dev"
Requires-Dist: isort>=5.12.0; extra == "dev"
Requires-Dist: flake8>=6.0.0; extra == "dev"
Requires-Dist: mypy>=1.5.0; extra == "dev"
Requires-Dist: pre-commit>=3.3.0; extra == "dev"
Requires-Dist: tox>=4.6.0; extra == "dev"
Provides-Extra: docs
Requires-Dist: sphinx>=7.0.0; extra == "docs"
Requires-Dist: sphinx-rtd-theme>=1.3.0; extra == "docs"
Requires-Dist: myst-parser>=2.0.0; extra == "docs"
Provides-Extra: deploy
Requires-Dist: docker>=6.1.0; extra == "deploy"
Requires-Dist: kubernetes>=26.1.0; extra == "deploy"
Requires-Dist: helm>=0.1.0; extra == "deploy"
Requires-Dist: terraform>=0.1.0; extra == "deploy"
Dynamic: license-file
